triggerkit/__init__.py
triggerkit/_modidx.py
triggerkit/actions.py
triggerkit/app.py
triggerkit/core.py
triggerkit/jobs.py
triggerkit/shared_actions.py
triggerkit/snowflake.py
triggerkit/util.py
triggerkit-0.0.1.dist-info/METADATA
triggerkit-0.0.1.dist-info/WHEEL
triggerkit-0.0.1.dist-info/entry_points.txt
triggerkit-0.0.1.dist-info/top_level.txt
triggerkit-0.0.1.dist-info/RECORD
