Metadata-Version: 2.4
Name: triggerkit
Version: 0.0.1
Summary: Modular kit for trigger-based actions
Home-page: https://github.com/Datatistics/triggerkit
Author: Cooper Richason
Author-email: 144618753+cooper-richason@users.noreply.github.com
Keywords: nbdev jupyter notebook python
Classifier: Development Status :: 4 - Beta
Classifier: Intended Audience :: Developers
Classifier: Natural Language :: English
Classifier: Programming Language :: Python :: 3.7
Classifier: Programming Language :: Python :: 3.8
Classifier: Programming Language :: Python :: 3.9
Classifier: Programming Language :: Python :: 3.10
Classifier: Programming Language :: Python :: 3.11
Classifier: Programming Language :: Python :: 3.12
Requires-Python: >=3.7
Requires-Dist: fastcore
Requires-Dist: nbdev
Requires-Dist: pandas
Requires-Dist: toml
Requires-Dist: snowflake-connector-python
Requires-Dist: schedule
Requires-Dist: apscheduler
Provides-Extra: dev
Dynamic: author
Dynamic: author-email
Dynamic: classifier
Dynamic: description
Dynamic: description-content-type
Dynamic: home-page
Dynamic: keywords
Dynamic: provides-extra
Dynamic: requires-dist
Dynamic: requires-python
Dynamic: summary
